htruc/__init__.py
htruc/catalog.py
htruc/cli.py
htruc/types.py
htruc/utils.py
htruc/validator.py
htruc/repos/__init__.py
htruc/repos/_generic.py
htruc/repos/_github.py
htruc/schemas/__init__.py
htruc/schemas/upgrade_path.py
htruc-1.1.3.dist-info/LICENSE.md
htruc-1.1.3.dist-info/METADATA
htruc-1.1.3.dist-info/WHEEL
htruc-1.1.3.dist-info/entry_points.txt
htruc-1.1.3.dist-info/top_level.txt
htruc-1.1.3.dist-info/RECORD
